README.md
setup.py
bens_calculator/__init__.py
bens_calculator/bens_calculator.py
bens_calculator.egg-info/PKG-INFO
bens_calculator.egg-info/SOURCES.txt
bens_calculator.egg-info/dependency_links.txt
bens_calculator.egg-info/top_level.txt