Metadata-Version: 2.1
Name: bens-calculator
Version: 0.0.1
Summary: A simple calculator for adding and multiplying two numbers
Author: Ben Brownlie
